{
  "url": "https://www.hkej.com/instantnews/current/article/4257780/%E5%AE%8F%E7%A6%8F%E8%8B%91%E4%BA%94%E7%B4%9A%E7%81%AB%E4%B8%A8%E6%9D%8E%E5%AE%B6%E8%B6%85%E5%88%B0%E7%81%AB%E8%AD%A6%E7%8F%BE%E5%A0%B4%E8%A6%96%E5%AF%9F+%E7%A8%8D%E5%BE%8C%E8%A6%8B%E5%82%B3%E5%AA%92",
  "title": "宏福苑五級火丨李家超到火警現場視察 稍後見傳媒",
  "source": "信報財經新聞",
  "source_file": "content/news/信報財經新聞/Readme.md",
  "scraped_at": "2025-11-29T01:48:57.613611",
  "archive_path": "content/news/信報財經新聞/archive/宏福苑五級火丨李家超到火警現場視察-稍後見傳媒"
}