{
  "url": "https://www.hkej.com/instantnews/current/article/4258762/%E5%AE%8F%E7%A6%8F%E8%8B%91%E4%BA%94%E7%B4%9A%E7%81%AB%E4%B8%A8%E6%B8%AF%E6%BE%B3%E8%BE%A6%E6%96%87%E7%AB%A0%3A%E8%A1%8C%E6%94%BF%E9%95%B7%E5%AE%98%E5%92%8C%E7%89%B9%E5%8D%80%E6%94%BF%E5%BA%9C%E6%9C%89%E5%8A%9B%E6%9C%89%E6%95%88%E6%87%89%E5%B0%8D%E8%99%95%E7%BD%AE",
  "title": "宏福苑五級火丨港澳辦文章:行政長官和特區政府有力有效應對處置",
  "source": "信報財經新聞",
  "source_file": "content/news/信報財經新聞/Readme.md",
  "scraped_at": "2025-11-29T01:54:45.632923",
  "archive_path": "content/news/信報財經新聞/archive/宏福苑五級火丨港澳辦文章行政長官和特區政府有力有效應對處置"
}